notaryjerk/LoadCommand.py
notaryjerk/MachO.py
notaryjerk/__init__.py
notaryjerk/__main__.py
notaryjerk/_version.py
notaryjerk/notarize.py
notaryjerk/staple.py
notaryjerk/utilities.py
notaryjerk-0.1.1.dist-info/licenses/LICENSE.md
notaryjerk-0.1.1.dist-info/METADATA
notaryjerk-0.1.1.dist-info/WHEEL
notaryjerk-0.1.1.dist-info/entry_points.txt
notaryjerk-0.1.1.dist-info/top_level.txt
notaryjerk-0.1.1.dist-info/RECORD
