Metadata-Version: 2.4
Name: notaryjerk
Version: 0.1.1
Summary: tools for codesigning and notarization of binaries
Author-email: IOhannes m zmölnig <zmoelnig@iem.at>
License: GNU Affero General Public License
Project-URL: Homepage, https://git.iem.at/zmoelnig/notaryjerk
Project-URL: Documentation, https://notaryjerk.readthedocs.io/
Project-URL: Repository, https://git.iem.at/devtools/notaryjerk.git
Project-URL: Issues, https://git.iem.at/zmoelnig/notaryjerk/-/issues
Classifier: Programming Language :: Python :: 3
Classifier: License :: OSI Approved :: GNU Affero General Public License v3 or later (AGPLv3+)
Classifier: Operating System :: OS Independent
Classifier: Development Status :: 3 - Alpha
Classifier: Environment :: Console
Classifier: Intended Audience :: Developers
Classifier: Topic :: System :: Software Distribution
Requires-Python: >=3.8
License-File: LICENSE.md
Requires-Dist: requests
Requires-Dist: boto3
Requires-Dist: authlib
Requires-Dist: asn1crypto
Dynamic: license-file
